iu2frl_civ/__init__.py
iu2frl_civ/device_base.py
iu2frl_civ/device_factory.py
iu2frl_civ/enums.py
iu2frl_civ/exceptions.py
iu2frl_civ/fakeserial.py
iu2frl_civ/utils.py
iu2frl_civ/devices/__init__.py
iu2frl_civ/devices/generic.py
iu2frl_civ/devices/ic706_mkii.py
iu2frl_civ/devices/ic7300.py
iu2frl_civ/devices/ic821h.py
iu2frl_civ-0.3.0.dist-info/licenses/CODE_OF_CONDUCT.md
iu2frl_civ-0.3.0.dist-info/licenses/CONTRIBUTING.md
iu2frl_civ-0.3.0.dist-info/licenses/LICENSE
iu2frl_civ-0.3.0.dist-info/licenses/README.md
iu2frl_civ-0.3.0.dist-info/licenses/SECURITY.md
iu2frl_civ-0.3.0.dist-info/METADATA
iu2frl_civ-0.3.0.dist-info/WHEEL
iu2frl_civ-0.3.0.dist-info/entry_points.txt
iu2frl_civ-0.3.0.dist-info/top_level.txt
iu2frl_civ-0.3.0.dist-info/RECORD
