Metadata-Version: 2.4
Name: iu2frl-civ
Version: 0.3.0
Summary: A small library to communicate with ICOM devices using CI-V protocol
Author-email: Luca Bennati <lucabennati1996@gmail.com>
Project-URL: Homepage, https://github.com/iu2frl/iu2frl_civ
Project-URL: Source, https://github.com/iu2frl/iu2frl_civ
Project-URL: Issues, https://github.com/iu2frl/iu2frl_civ/issues
Keywords: icom,ci-v,transceivers,communication
Classifier: Development Status :: 4 - Beta
Classifier: Intended Audience :: Developers
Classifier: Programming Language :: Python
Classifier: Programming Language :: Python :: 3
Classifier: Programming Language :: Python :: 3.10
Classifier: Programming Language :: Python :: 3.11
Classifier: Programming Language :: Python :: 3.12
Classifier: Operating System :: OS Independent
Requires-Python: >=3.8
License-File: LICENSE
License-File: CODE_OF_CONDUCT.md
License-File: CONTRIBUTING.md
License-File: SECURITY.md
License-File: README.md
Requires-Dist: pyserial==3.5
Dynamic: license-file
